conjunto/__init__.py
conjunto/admin.py
conjunto/apps.py
conjunto/colors.py
conjunto/context_processors.py
conjunto/fields.py
conjunto/gdaps_hooks.py
conjunto/menus.py
conjunto/middleware.py
conjunto/models.py
conjunto/registry.py
conjunto/tables.py
conjunto/tools.py
conjunto/urls.py
conjunto/views.py
conjunto/api/__init__.py
conjunto/api/interfaces/__init__.py
conjunto/api/interfaces/settings.py
conjunto/audit_log/__init__.py
conjunto/audit_log/context.py
conjunto/audit_log/formatter.py
conjunto/audit_log/gdaps_hooks.py
conjunto/audit_log/log_actions.py
conjunto/audit_log/models.py
conjunto/audit_log/registry.py
conjunto/audit_log/migrations/0001_initial.py
conjunto/audit_log/migrations/0002_modellogentry_public_and_more.py
conjunto/audit_log/migrations/0003_modellogentry_result.py
conjunto/audit_log/migrations/__init__.py
conjunto/cms/README.md
conjunto/cms/__init__.py
conjunto/cms/admin.py
conjunto/cms/apps.py
conjunto/cms/models.py
conjunto/cms/tests.py
conjunto/cms/views.py
conjunto/cms/migrations/0001_initial.py
conjunto/cms/migrations/0002_delete_staticversionedpage_alter_licensepage_options_and_more.py
conjunto/cms/migrations/0003_rename_licensepage_termsconditionspage.py
conjunto/cms/migrations/0004_alter_termsconditionspage_options.py
conjunto/cms/migrations/0005_alter_privacypage_version_and_more.py
conjunto/cms/migrations/0006_staticpage_name.py
conjunto/cms/migrations/__init__.py
conjunto/cms/templates/conjunto/cms/static_page.html
conjunto/components/__init__.py
conjunto/components/default/__init__.py
conjunto/components/default/card/__init__.py
conjunto/components/default/card/card.html
conjunto/components/default/modal/__init__.py
conjunto/components/default/modal/modal.html
conjunto/components/default/settings_widget/__init__.py
conjunto/components/default/settings_widget/settings_widget.html
conjunto/components/default/toasts/__init__.py
conjunto/components/default/toasts/toasts.html
conjunto/components/default/toasts/toasts.js
conjunto-0.0.25.dist-info/licenses/LICENSE
conjunto-0.0.25.dist-info/METADATA
conjunto-0.0.25.dist-info/WHEEL
conjunto-0.0.25.dist-info/top_level.txt
conjunto-0.0.25.dist-info/RECORD
