Metadata-Version: 2.4
Name: conjunto
Version: 0.0.25
Summary: Django application framework/helpers using Tetra, tabler.io, tables2, crispy-forms & more.
Author-email: Christian González <christian.gonzalez@nerdocs.at>
License-Expression: MIT
Project-URL: Homepage, https://github.com/nerdocs/conjunto
Project-URL: Repository, https://github.com/nerdocs/conjunto
Keywords: python,django,tetra,framework,i18n
Classifier: Development Status :: 2 - Pre-Alpha
Classifier: Programming Language :: Python
License-File: LICENSE
Requires-Dist: django>=5.1
Requires-Dist: django-countries
Requires-Dist: django-phonenumber-field[phonenumberslite]
Requires-Dist: django-crispy-forms
Requires-Dist: crispy-bootstrap5
Requires-Dist: django-tables2
Requires-Dist: django-versionfield
Requires-Dist: django-markdownify
Requires-Dist: django-web-components
Requires-Dist: django-statici18n
Requires-Dist: gdaps>=0.10.0
Requires-Dist: django-extensions>=3.2
Requires-Dist: Pillow
Requires-Dist: tetra>=0.2
Provides-Extra: dev
Requires-Dist: conjunto[prod]; extra == "dev"
Requires-Dist: build; extra == "dev"
Requires-Dist: twine; extra == "dev"
Requires-Dist: pytest; extra == "dev"
Requires-Dist: pytest-mock; extra == "dev"
Requires-Dist: pytest-django; extra == "dev"
Requires-Dist: pre-commit; extra == "dev"
Requires-Dist: black; extra == "dev"
Provides-Extra: doc
Requires-Dist: mkdocs; extra == "doc"
Requires-Dist: mkdocstrings-python; extra == "doc"
Requires-Dist: mkdocs-literate-nav; extra == "doc"
Requires-Dist: mkdocs-section-index; extra == "doc"
Requires-Dist: pymdown-extensions; extra == "doc"
Requires-Dist: pygments; extra == "doc"
Requires-Dist: mkdocs-api-autonav; extra == "doc"
Provides-Extra: prod
Dynamic: license-file
